analogainas/__init__.py
analogainas/__version__.py
analogainas/utils.py
analogainas/evaluators/__init__.py
analogainas/evaluators/base_evaluator.py
analogainas/evaluators/mlp.py
analogainas/evaluators/prepare_data.py
analogainas/evaluators/xgboost.py
analogainas/search_algorithms/__init__.py
analogainas/search_algorithms/bo.py
analogainas/search_algorithms/ea.py
analogainas/search_algorithms/ea_optimized.py
analogainas/search_algorithms/worker.py
analogainas-0.1.0.dist-info/LICENSE
analogainas-0.1.0.dist-info/METADATA
analogainas-0.1.0.dist-info/WHEEL
analogainas-0.1.0.dist-info/top_level.txt
analogainas-0.1.0.dist-info/RECORD
