Metadata-Version: 2.1
Name: analogainas
Version: 0.1.0
Summary: AnalogAINAS: A modular and extensible Analog-aware Neural Architecture Search (NAS) library.
Home-page: https://github.com/IBM/analog-nas
Author: IBM Research
Author-email: aihwkit@us.ibm.com
License: Apache 2.0
Keywords: NAS,analog,torch
Platform: Linux
Classifier: Development Status :: 4 - Beta
Classifier: Environment :: Console
Classifier: Environment :: GPU :: NVIDIA CUDA
Classifier: Intended Audience :: Science/Research
Classifier: License :: OSI Approved :: Apache Software License
Classifier: Operating System :: MacOS
Classifier: Operating System :: Microsoft :: Windows
Classifier: Operating System :: POSIX :: Linux
Classifier: Programming Language :: Python :: 3 :: Only
Classifier: Topic :: Scientific/Engineering
Classifier: Topic :: Scientific/Engineering :: Artificial Intelligence
Classifier: Typing :: Typed
Requires-Python: >=3.7
License-File: LICENSE
Requires-Dist: torch (>=1.9)
Requires-Dist: torchvision
Requires-Dist: scipy
Requires-Dist: numpy (>=1.19)
Requires-Dist: xgboost
